knai/__init__.py
knai/client.py
knai/errors.py
knai_provider-0.1.0.dist-info/licenses/LICENSE
knai_provider-0.1.0.dist-info/METADATA
knai_provider-0.1.0.dist-info/WHEEL
knai_provider-0.1.0.dist-info/top_level.txt
knai_provider-0.1.0.dist-info/RECORD
