Metadata-Version: 2.4
Name: knai-provider
Version: 0.1.0
Summary: Python SDK for KNAI Wallet provider integration
Home-page: https://knai.app
Author: KNAI
Author-email: KNAI <support@knai.app>
License: MIT
Project-URL: Homepage, https://knai.app
Project-URL: Documentation, https://docs.knai.app
Project-URL: Repository, https://github.com/knai-app/knai-python
Keywords: knai,wallet,fintech,ai,sdk,payments
Classifier: Development Status :: 4 - Beta
Classifier: Intended Audience :: Developers
Classifier: License :: OSI Approved :: MIT License
Classifier: Operating System :: OS Independent
Classifier: Programming Language :: Python :: 3
Classifier: Programming Language :: Python :: 3.8
Classifier: Programming Language :: Python :: 3.9
Classifier: Programming Language :: Python :: 3.10
Classifier: Programming Language :: Python :: 3.11
Classifier: Programming Language :: Python :: 3.12
Classifier: Topic :: Software Development :: Libraries :: Python Modules
Requires-Python: >=3.8
License-File: LICENSE
Requires-Dist: requests>=2.25
Dynamic: license-file
